recom/__init__.py
recom/__main__.py
recom/cli.py
recom/device.py
recom/exceptions.py
recom/interface.py
recom/util.py
recom/backend/__init__.py
recom/backend/backend.py
recom/backend/uart.py
recom/backend/usb.py
recom-0.1.1.dist-info/METADATA
recom-0.1.1.dist-info/WHEEL
recom-0.1.1.dist-info/entry_points.txt
recom-0.1.1.dist-info/top_level.txt
recom-0.1.1.dist-info/RECORD
