Metadata-Version: 2.2
Name: recom
Version: 0.1.1
Summary: Embedded communication backend
Home-page: https://github.com/redhill-embedded/recom.git
Author: Adrian Rothenbuhler
Author-email: adrian@redhill-embedded.com
License: MIT
Keywords: embedded communication backedn usb serial
Requires-Python: >=3.8
Requires-Dist: libusb1
Requires-Dist: pyserial
Requires-Dist: pyudev
Requires-Dist: psutil
Dynamic: author
Dynamic: author-email
Dynamic: home-page
Dynamic: keywords
Dynamic: license
Dynamic: requires-dist
Dynamic: requires-python
Dynamic: summary
